package_utils/__init__.py
package_utils/py.typed
package_utils/cli/__init__.py
package_utils/cli/cli_runner.py
package_utils/cli/entry_point.py
package_utils/cli/convertors/__init__.py
package_utils/cli/convertors/class_.py
package_utils/cli/convertors/dataclass.py
package_utils/cli/convertors/method.py
package_utils/cli/convertors/parameter.py
package_utils/context/__init__.py
package_utils/context/context.py
package_utils/context/entry_point.py
package_utils/context/loaders/__init__.py
package_utils/context/loaders/config.py
package_utils/context/loaders/loaders.py
package_utils/context/loaders/options.py
package_utils/context/loaders/secrets_.py
package_utils/context/models/__init__.py
package_utils/context/models/models.py
package_utils/dataclasses/__init__.py
package_utils/dataclasses/mixins.py
package_utils/jobs/__init__.py
package_utils/jobs/jobs.py
package_utils/storage/__init__.py
package_utils/storage/cached_file_content.py
package_utils-0.8.1.dist-info/licenses/LICENSE
package_utils-0.8.1.dist-info/METADATA
package_utils-0.8.1.dist-info/WHEEL
package_utils-0.8.1.dist-info/top_level.txt
package_utils-0.8.1.dist-info/RECORD
