Metadata-Version: 2.4
Name: package-utils
Version: 0.8.1
Summary: Common utilities for Python packages
Author-email: Quinten Roets <qdr2104@columbia.edu>
License-Expression: MIT
Project-URL: Source Code, https://github.com/quintenroets/package-utils
Requires-Python: <3.14,>=3.10
License-File: LICENSE
Requires-Dist: typer<1,>=0.9.0
Provides-Extra: context
Requires-Dist: dacite<2,>=1.8.1; extra == "context"
Requires-Dist: powercli<1,>=0.2.0; extra == "context"
Requires-Dist: PyYaml<7,>=6.0.1; extra == "context"
Requires-Dist: superpathlib<3,>=2.0.0; extra == "context"
Provides-Extra: dataclasses
Requires-Dist: dacite<2,>=1.8.1; extra == "dataclasses"
Provides-Extra: storage
Requires-Dist: superpathlib<3,>=2.0.0; extra == "storage"
Provides-Extra: dev
Requires-Dist: dacite<2,>=1.8.1; extra == "dev"
Requires-Dist: PyYaml<7,>=6.0.1; extra == "dev"
Requires-Dist: superpathlib<3,>=2.0.0; extra == "dev"
Requires-Dist: hypothesis<7,>=6.91.0; extra == "dev"
Requires-Dist: package-dev-tools<1,>=0.7.1; extra == "dev"
Requires-Dist: package-dev-utils<1,>=0.1.6; extra == "dev"
Dynamic: license-file
